[{"name": "apparent_temp_benchmarks.TimeSuite.time_apparent_temperature", "idx": null, "pretty_name": "apparent_temp_benchmarks.TimeSuite.time_apparent_temperature", "last_rev": 9388, "last_value": 0.003693645833341937, "last_err": 0.0, "prev_value": null, "change_rev": null}, {"name": "apparent_temp_benchmarks.TimeSuite.time_heat_index", "idx": null, "pretty_name": "apparent_temp_benchmarks.TimeSuite.time_heat_index", "last_rev": 9388, "last_value": 0.015260006000005433, "last_err": 0.0, "prev_value": null, "change_rev": null}, {"name": "apparent_temp_benchmarks.TimeSuite.time_windchill", "idx": null, "pretty_name": "apparent_temp_benchmarks.TimeSuite.time_windchill", "last_rev": 9388, "last_value": 0.010859731750002766, "last_err": 0.0, "prev_value": null, "change_rev": null}, {"name": "bound_layer_turbulence_benchmarks.TimeSuite.time_brunt_vaisala_frequency", "idx": null, "pretty_name": "bound_layer_turbulence_benchmarks.TimeSuite.time_brunt_vaisala_frequency", "last_rev": 9388, "last_value": 0.006789864249995503, "last_err": 0.0, "prev_value": null, "change_rev": null}, {"name": "bound_layer_turbulence_benchmarks.TimeSuite.time_gradient_richardson_number", "idx": null, "pretty_name": "bound_layer_turbulence_benchmarks.TimeSuite.time_gradient_richardson_number", "last_rev": 9388, "last_value": 0.012151619999997365, "last_err": 0.0, "prev_value": null, "change_rev": null}, {"name": "dry_thermo_benchmarks.TimeSuite.time_density", "idx": null, "pretty_name": "dry_thermo_benchmarks.TimeSuite.time_density", "last_rev": 9388, "last_value": 0.003579556666674459, "last_err": 0.0, "prev_value": null, "change_rev": null}, {"name": "dry_thermo_benchmarks.TimeSuite.time_dry_lapse", "idx": null, "pretty_name": "dry_thermo_benchmarks.TimeSuite.time_dry_lapse", "last_rev": 9388, "last_value": 0.006626019000009364, "last_err": 0.0, "prev_value": null, "change_rev": null}, {"name": "dry_thermo_benchmarks.TimeSuite.time_height_to_geopotential", "idx": null, "pretty_name": "dry_thermo_benchmarks.TimeSuite.time_height_to_geopotential", "last_rev": 9388, "last_value": 0.0025215023999976436, "last_err": 0.0, "prev_value": null, "change_rev": null}, {"name": "dry_thermo_benchmarks.TimeSuite.time_potential_temperature", "idx": null, "pretty_name": "dry_thermo_benchmarks.TimeSuite.time_potential_temperature", "last_rev": 9388, "last_value": 0.006981464250003455, "last_err": 0.0, "prev_value": null, "change_rev": null}, {"name": "dry_thermo_benchmarks.TimeSuite.time_static_stability", "idx": null, "pretty_name": "dry_thermo_benchmarks.TimeSuite.time_static_stability", "last_rev": 9388, "last_value": 0.01015271899998993, "last_err": 0.0, "prev_value": null, "change_rev": null}, {"name": "dry_thermo_benchmarks.TimeSuite.time_thickness_hydrostatic", "idx": null, "pretty_name": "dry_thermo_benchmarks.TimeSuite.time_thickness_hydrostatic", "last_rev": 9388, "last_value": 0.0009626339583353645, "last_err": 0.0, "prev_value": null, "change_rev": null}, {"name": "dyn_kin_benchmarks.TimeSuite.time_absolute_vorticity", "idx": null, "pretty_name": "dyn_kin_benchmarks.TimeSuite.time_absolute_vorticity", "last_rev": 9388, "last_value": 0.011396030500009147, "last_err": 0.0, "prev_value": null, "change_rev": null}, {"name": "dyn_kin_benchmarks.TimeSuite.time_advection", "idx": null, "pretty_name": "dyn_kin_benchmarks.TimeSuite.time_advection", "last_rev": 9388, "last_value": 0.014643292499982863, "last_err": 0.0, "prev_value": null, "change_rev": null}, {"name": "dyn_kin_benchmarks.TimeSuite.time_ageostrophic_wind", "idx": null, "pretty_name": "dyn_kin_benchmarks.TimeSuite.time_ageostrophic_wind", "last_rev": 9388, "last_value": 0.011521445499965921, "last_err": 0.0, "prev_value": null, "change_rev": null}, {"name": "dyn_kin_benchmarks.TimeSuite.time_frontogenesis", "idx": null, "pretty_name": "dyn_kin_benchmarks.TimeSuite.time_frontogenesis", "last_rev": 9388, "last_value": 0.024939982499972757, "last_err": 0.0, "prev_value": null, "change_rev": null}, {"name": "dyn_kin_benchmarks.TimeSuite.time_potential_vorticity_barotropic", "idx": null, "pretty_name": "dyn_kin_benchmarks.TimeSuite.time_potential_vorticity_barotropic", "last_rev": 9388, "last_value": 0.025403879999998935, "last_err": 0.0, "prev_value": null, "change_rev": null}, {"name": "dyn_kin_benchmarks.TimeSuite.time_q_vector", "idx": null, "pretty_name": "dyn_kin_benchmarks.TimeSuite.time_q_vector", "last_rev": 9388, "last_value": 0.016496563000004016, "last_err": 0.0, "prev_value": null, "change_rev": null}, {"name": "dyn_kin_benchmarks.TimeSuite.time_total_deformation", "idx": null, "pretty_name": "dyn_kin_benchmarks.TimeSuite.time_total_deformation", "last_rev": 9388, "last_value": 0.012255350000003773, "last_err": 0.0, "prev_value": null, "change_rev": null}, {"name": "dyn_kin_benchmarks.TimeSuite.time_vorticity", "idx": null, "pretty_name": "dyn_kin_benchmarks.TimeSuite.time_vorticity", "last_rev": 9388, "last_value": 0.010390438999991147, "last_err": 0.0, "prev_value": null, "change_rev": null}, {"name": "math_fctn_benchmarks.TimeSuite.time_geospatial_gradient", "idx": null, "pretty_name": "math_fctn_benchmarks.TimeSuite.time_geospatial_gradient", "last_rev": 9388, "last_value": 0.007001762750007856, "last_err": 0.0, "prev_value": null, "change_rev": null}, {"name": "math_fctn_benchmarks.TimeSuite.time_geospatial_laplacian", "idx": null, "pretty_name": "math_fctn_benchmarks.TimeSuite.time_geospatial_laplacian", "last_rev": 9388, "last_value": 0.011257108000023663, "last_err": 0.0, "prev_value": null, "change_rev": null}, {"name": "math_fctn_benchmarks.TimeSuite.time_gradient", "idx": null, "pretty_name": "math_fctn_benchmarks.TimeSuite.time_gradient", "last_rev": 9388, "last_value": 0.02164612750001993, "last_err": 0.0, "prev_value": null, "change_rev": null}, {"name": "math_fctn_benchmarks.TimeSuite.time_vector_derivative", "idx": null, "pretty_name": "math_fctn_benchmarks.TimeSuite.time_vector_derivative", "last_rev": 9388, "last_value": 0.01105332949998683, "last_err": 0.0, "prev_value": null, "change_rev": null}, {"name": "moist_thermo_benchmarks.TimeSuite.time_dewpoint", "idx": null, "pretty_name": "moist_thermo_benchmarks.TimeSuite.time_dewpoint", "last_rev": 9388, "last_value": 0.0030753866250066153, "last_err": 0.0, "prev_value": null, "change_rev": null}, {"name": "moist_thermo_benchmarks.TimeSuite.time_dewpoint_from_rh", "idx": null, "pretty_name": "moist_thermo_benchmarks.TimeSuite.time_dewpoint_from_rh", "last_rev": 9388, "last_value": 0.006359076250006979, "last_err": 0.0, "prev_value": null, "change_rev": null}, {"name": "moist_thermo_benchmarks.TimeSuite.time_precipitable_water", "idx": null, "pretty_name": "moist_thermo_benchmarks.TimeSuite.time_precipitable_water", "last_rev": 9388, "last_value": 0.004091796833326574, "last_err": 0.0, "prev_value": null, "change_rev": null}, {"name": "moist_thermo_benchmarks.TimeSuite.time_rh_from_mixing_ratio", "idx": null, "pretty_name": "moist_thermo_benchmarks.TimeSuite.time_rh_from_mixing_ratio", "last_rev": 9388, "last_value": 0.007108098750009617, "last_err": 0.0, "prev_value": null, "change_rev": null}, {"name": "moist_thermo_benchmarks.TimeSuite.time_saturation_vapor_pressure", "idx": null, "pretty_name": "moist_thermo_benchmarks.TimeSuite.time_saturation_vapor_pressure", "last_rev": 9388, "last_value": 0.002847215000002734, "last_err": 0.0, "prev_value": null, "change_rev": null}, {"name": "moist_thermo_benchmarks.TimeSuite.time_scale_height", "idx": null, "pretty_name": "moist_thermo_benchmarks.TimeSuite.time_scale_height", "last_rev": 9388, "last_value": 0.002686372874990184, "last_err": 0.0, "prev_value": null, "change_rev": null}, {"name": "moist_thermo_benchmarks.TimeSuite.time_virtual_temperature", "idx": null, "pretty_name": "moist_thermo_benchmarks.TimeSuite.time_virtual_temperature", "last_rev": 9388, "last_value": 0.0053101867499947275, "last_err": 0.0, "prev_value": null, "change_rev": null}, {"name": "moist_thermo_benchmarks.TimeSuite.time_wet_bulb_temperature", "idx": null, "pretty_name": "moist_thermo_benchmarks.TimeSuite.time_wet_bulb_temperature", "last_rev": 9388, "last_value": 1.4270739170000013, "last_err": 0.0, "prev_value": null, "change_rev": null}, {"name": "other_benchmarks.TimeSuite.time_find_intersections", "idx": null, "pretty_name": "other_benchmarks.TimeSuite.time_find_intersections", "last_rev": 9388, "last_value": 0.00039274735714351597, "last_err": 0.0, "prev_value": null, "change_rev": null}, {"name": "other_benchmarks.TimeSuite.time_find_peaks", "idx": null, "pretty_name": "other_benchmarks.TimeSuite.time_find_peaks", "last_rev": null, "last_value": null, "last_err": null, "prev_value": null, "change_rev": null}, {"name": "other_benchmarks.TimeSuite.time_get_perturbation", "idx": null, "pretty_name": "other_benchmarks.TimeSuite.time_get_perturbation", "last_rev": 9388, "last_value": 0.012228900000025078, "last_err": 0.0, "prev_value": null, "change_rev": null}, {"name": "other_benchmarks.TimeSuite.time_peak_persistence", "idx": null, "pretty_name": "other_benchmarks.TimeSuite.time_peak_persistence", "last_rev": null, "last_value": null, "last_err": null, "prev_value": null, "change_rev": null}, {"name": "smoothing_benchmarks.TimeSuite.time_smooth_circular", "idx": null, "pretty_name": "smoothing_benchmarks.TimeSuite.time_smooth_circular", "last_rev": 9388, "last_value": 0.0012278556666653155, "last_err": 0.0, "prev_value": null, "change_rev": null}, {"name": "smoothing_benchmarks.TimeSuite.time_smooth_gaussian", "idx": null, "pretty_name": "smoothing_benchmarks.TimeSuite.time_smooth_gaussian", "last_rev": 9388, "last_value": 0.0010629088500024864, "last_err": 0.0, "prev_value": null, "change_rev": null}, {"name": "smoothing_benchmarks.TimeSuite.time_smooth_n_point", "idx": null, "pretty_name": "smoothing_benchmarks.TimeSuite.time_smooth_n_point", "last_rev": 9388, "last_value": 0.0010519076363664226, "last_err": 0.0, "prev_value": null, "change_rev": null}, {"name": "smoothing_benchmarks.TimeSuite.time_smooth_rectangular", "idx": null, "pretty_name": "smoothing_benchmarks.TimeSuite.time_smooth_rectangular", "last_rev": 9388, "last_value": 0.001123561900001846, "last_err": 0.0, "prev_value": null, "change_rev": null}, {"name": "smoothing_benchmarks.TimeSuite.time_smooth_window", "idx": null, "pretty_name": "smoothing_benchmarks.TimeSuite.time_smooth_window", "last_rev": 9388, "last_value": 0.001169558888888231, "last_err": 0.0, "prev_value": null, "change_rev": null}, {"name": "soundings_benchmarks.TimeSuite.time_bulk_shear", "idx": null, "pretty_name": "soundings_benchmarks.TimeSuite.time_bulk_shear", "last_rev": 9388, "last_value": 0.0035898458333273693, "last_err": 0.0, "prev_value": null, "change_rev": null}, {"name": "soundings_benchmarks.TimeSuite.time_cape_cin", "idx": null, "pretty_name": "soundings_benchmarks.TimeSuite.time_cape_cin", "last_rev": 9388, "last_value": 0.0027762319999951046, "last_err": 0.0, "prev_value": null, "change_rev": null}, {"name": "soundings_benchmarks.TimeSuite.time_ccl", "idx": null, "pretty_name": "soundings_benchmarks.TimeSuite.time_ccl", "last_rev": 9388, "last_value": 0.001316429333336878, "last_err": 0.0, "prev_value": null, "change_rev": null}, {"name": "soundings_benchmarks.TimeSuite.time_el", "idx": null, "pretty_name": "soundings_benchmarks.TimeSuite.time_el", "last_rev": 9388, "last_value": 0.005630918999997903, "last_err": 0.0, "prev_value": null, "change_rev": null}, {"name": "soundings_benchmarks.TimeSuite.time_lcl", "idx": null, "pretty_name": "soundings_benchmarks.TimeSuite.time_lcl", "last_rev": 9388, "last_value": 0.0340689120000377, "last_err": 0.0, "prev_value": null, "change_rev": null}, {"name": "soundings_benchmarks.TimeSuite.time_most_unstable_parcel", "idx": null, "pretty_name": "soundings_benchmarks.TimeSuite.time_most_unstable_parcel", "last_rev": 9388, "last_value": 0.003296281875002194, "last_err": 0.0, "prev_value": null, "change_rev": null}, {"name": "soundings_benchmarks.TimeSuite.time_parcel_profile", "idx": null, "pretty_name": "soundings_benchmarks.TimeSuite.time_parcel_profile", "last_rev": 9388, "last_value": 0.0052364902499988375, "last_err": 0.0, "prev_value": null, "change_rev": null}, {"name": "std_atm_benchmarks.TimeSuite.time_height_to_pressure_std", "idx": null, "pretty_name": "std_atm_benchmarks.TimeSuite.time_height_to_pressure_std", "last_rev": 9388, "last_value": 0.003799181000005092, "last_err": 0.0, "prev_value": null, "change_rev": null}, {"name": "std_atm_benchmarks.TimeSuite.time_pressure_to_height_std", "idx": null, "pretty_name": "std_atm_benchmarks.TimeSuite.time_pressure_to_height_std", "last_rev": 9388, "last_value": 0.0011971535555548802, "last_err": 0.0, "prev_value": null, "change_rev": null}]